{
  "buffer_size": 10,
  "sequence": [
    {
      "step": 1,
      "id": 1,
      "size": [
        0.178,
        0.195,
        0.134
      ],
      "mass": 0.5,
      "position": [
        0.089,
        0.098,
        0.067
      ],
      "rotation": 90
    },
    {
      "step": 8,
      "id": 8,
      "size": [
        0.22,
        0.245,
        0.158
      ],
      "mass": 2.0,
      "position": [
        0.11,
        0.343,
        0.079
      ],
      "rotation": 90
    },
    {
      "step": 7,
      "id": 7,
      "size": [
        0.178,
        0.195,
        0.134
      ],
      "mass": 0.5,
      "position": [
        0.089,
        0.588,
        0.067
      ],
      "rotation": 90
    },
    {
      "step": 9,
      "id": 9,
      "size": [
        0.178,
        0.195,
        0.134
      ],
      "mass": 0.5,
      "position": [
        0.089,
        0.807,
        0.067
      ],
      "rotation": 90
    },
    {
      "step": 11,
      "id": 11,
      "size": [
        0.245,
        0.22,
        0.158
      ],
      "mass": 2.0,
      "position": [
        0.323,
        0.11,
        0.079
      ],
      "rotation": 0
    },
    {
      "step": 2,
      "id": 2,
      "size": [
        0.245,
        0.178,
        0.14
      ],
      "mass": 1.0,
      "position": [
        0.593,
        0.089,
        0.07
      ],
      "rotation": 0
    },
    {
      "step": 15,
      "id": 15,
      "size": [
        0.245,
        0.22,
        0.158
      ],
      "mass": 2.0,
      "position": [
        0.863,
        0.11,
        0.079
      ],
      "rotation": 0
    },
    {
      "step": 12,
      "id": 12,
      "size": [
        0.178,
        0.195,
        0.134
      ],
      "mass": 0.5,
      "position": [
        1.099,
        0.098,
        0.067
      ],
      "rotation": 90
    },
    {
      "step": 13,
      "id": 13,
      "size": [
        0.178,
        0.195,
        0.134
      ],
      "mass": 0.5,
      "position": [
        0.089,
        0.098,
        0.207
      ],
      "rotation": 90
    },
    {
      "step": 17,
      "id": 17,
      "size": [
        0.245,
        0.22,
        0.158
      ],
      "mass": 2.0,
      "position": [
        0.372,
        0.36,
        0.079
      ],
      "rotation": 0
    },
    {
      "step": 19,
      "id": 19,
      "size": [
        0.195,
        0.178,
        0.134
      ],
      "mass": 0.5,
      "position": [
        0.598,
        0.319,
        0.067
      ],
      "rotation": 0
    },
    {
      "step": 3,
      "id": 3,
      "size": [
        0.245,
        0.178,
        0.14
      ],
      "mass": 1.0,
      "position": [
        0.833,
        0.309,
        0.07
      ],
      "rotation": 0
    },
    {
      "step": 10,
      "id": 10,
      "size": [
        0.245,
        0.178,
        0.14
      ],
      "mass": 1.0,
      "position": [
        0.643,
        0.529,
        0.07
      ],
      "rotation": 0
    },
    {
      "step": 16,
      "id": 16,
      "size": [
        0.245,
        0.178,
        0.14
      ],
      "mass": 1.0,
      "position": [
        0.913,
        0.519,
        0.07
      ],
      "rotation": 0
    },
    {
      "step": 23,
      "id": 23,
      "size": [
        0.178,
        0.195,
        0.134
      ],
      "mass": 0.5,
      "position": [
        0.089,
        0.098,
        0.347
      ],
      "rotation": 90
    },
    {
      "step": 22,
      "id": 22,
      "size": [
        0.245,
        0.178,
        0.14
      ],
      "mass": 1.0,
      "position": [
        0.333,
        0.589,
        0.07
      ],
      "rotation": 0
    },
    {
      "step": 25,
      "id": 25,
      "size": [
        0.245,
        0.178,
        0.14
      ],
      "mass": 1.0,
      "position": [
        0.603,
        0.709,
        0.07
      ],
      "rotation": 0
    },
    {
      "step": 26,
      "id": 26,
      "size": [
        0.195,
        0.178,
        0.134
      ],
      "mass": 0.5,
      "position": [
        0.578,
        0.679,
        0.217
      ],
      "rotation": 0
    },
    {
      "step": 27,
      "id": 27,
      "size": [
        0.195,
        0.178,
        0.134
      ],
      "mass": 0.5,
      "position": [
        0.297,
        0.789,
        0.067
      ],
      "rotation": 0
    },
    {
      "step": 0,
      "id": 0,
      "size": [
        0.31,
        0.233,
        0.21
      ],
      "mass": 4.0,
      "position": [
        0.915,
        0.767,
        0.105
      ],
      "rotation": 0
    },
    {
      "step": 4,
      "id": 4,
      "size": [
        0.31,
        0.233,
        0.21
      ],
      "mass": 4.0,
      "position": [
        0.915,
        0.757,
        0.315
      ],
      "rotation": 0
    },
    {
      "step": 5,
      "id": 5,
      "size": [
        0.31,
        0.233,
        0.21
      ],
      "mass": 4.0,
      "position": [
        0.905,
        0.757,
        0.525
      ],
      "rotation": 0
    },
    {
      "step": 14,
      "id": 14,
      "size": [
        0.31,
        0.233,
        0.21
      ],
      "mass": 4.0,
      "position": [
        0.915,
        0.757,
        0.735
      ],
      "rotation": 0
    },
    {
      "step": 32,
      "id": 32,
      "size": [
        0.245,
        0.22,
        0.158
      ],
      "mass": 2.0,
      "position": [
        0.873,
        0.11,
        0.239
      ],
      "rotation": 0
    },
    {
      "step": 21,
      "id": 21,
      "size": [
        0.31,
        0.233,
        0.21
      ],
      "mass": 4.0,
      "position": [
        0.925,
        0.757,
        0.945
      ],
      "rotation": 0
    },
    {
      "step": 34,
      "id": 34,
      "size": [
        0.245,
        0.178,
        0.14
      ],
      "mass": 1.0,
      "position": [
        0.573,
        0.889,
        0.07
      ],
      "rotation": 0
    },
    {
      "step": 35,
      "id": 35,
      "size": [
        0.245,
        0.22,
        0.158
      ],
      "mass": 2.0,
      "position": [
        0.883,
        0.11,
        0.399
      ],
      "rotation": 0
    }
  ],
  "terminated": true,
  "terminated_step": 6,
  "finished_by_user": false
}